CS3650_P1_SingleCycle/data_memory_mod.v

//longterm data storage 
module data_memory  
 (  
      input                         clk,  
      // address input, shared by read and write port  
      input     [15:0]               mem_access_addr,  
      // write port  
      input     [15:0]               mem_write_data,  
      input                         mem_write_en,  
      input mem_read,  
      // read port  
      output     [15:0]               mem_read_data  
 );  
      integer i;  
      reg [15:0] ram [255:0];  //256 ram registers of 16bit size 
      wire [7 : 0] ram_addr = mem_access_addr[8 : 1];  
      initial begin  
           for(i=0;i<256;i=i+1)  
                ram[i] <= 16'd0;  //initialize all memory cells in ram to 0
      end  
      always @(posedge clk) begin  
           if (mem_write_en)  
                ram[ram_addr] <= mem_write_data;  
      end  
      assign mem_read_data = (mem_read==1'b1) ? ram[ram_addr]: 16'd0;   
 endmodule

CS3650_P1_SingleCycle/ALU_module.v
 module ALUControl( ALU_Control, ALUOp, Function);  
 output reg[2:0] ALU_Control;  
 input [1:0] ALUOp;  
 input [3:0] Function;  
 wire [5:0] ALUControlIn;  
 assign ALUControlIn = {ALUOp,Function};  
 always @(ALUControlIn)  
 casex (ALUControlIn)  
  6'b11xxxx: ALU_Control=3'b000;  
  6'b10xxxx: ALU_Control=3'b100;  
  6'b01xxxx: ALU_Control=3'b001;  
  6'b000000: ALU_Control=3'b000;  
  6'b000001: ALU_Control=3'b001;  
  6'b000010: ALU_Control=3'b010;  
  6'b000011: ALU_Control=3'b011;  
  6'b000100: ALU_Control=3'b100;  
  default: ALU_Control=3'b000;  
  endcase  
 endmodule  




//performs operation on some input data 
module alu(       
      input          [15:0]     a,          //src1  
      input          [15:0]     b,          //src2  
      input          [2:0]     alu_control,     //function sel  
      output     reg     [15:0]     result,          //result       
      output zero  
   );  
 always @(*)  //fpga4student.com: FPga projects, Verilog projects, VHDL projects
 begin   
      case(alu_control)  
      3'b000: result = a + b; // add  
      3'b001: result = a - b; // sub  
      3'b010: result = a & b; // and  
      3'b011: result = a | b; // or  
      3'b100: begin if (a<b) result = 16'd1;  
                     else result = 16'd0;  
                     end  
      default:result = a + b; // add  
      endcase  
 end  
 assign zero = (result==16'd0) ? 1'b1: 1'b0;  
 endmodule

CS3650_P1_SingleCycle/processor_module.v
`include "ALU_module.v"
`include "instruction_memory_mod.v"
`include "data_memory_mod.v"

//register file of the processor
    //where data is held temporarily for operations with 
module register_file  
 (  
      input                    clk,  
      input                    rst,  
      // write port  
      input                    reg_write_en,  
      input          [2:0]     reg_write_dest,  
      input          [15:0]     reg_write_data,  
      //read port 1  
      input          [2:0]     reg_read_addr_1,  
      output          [15:0]     reg_read_data_1,  
      //read port 2  
      input          [2:0]     reg_read_addr_2,  
      output          [15:0]     reg_read_data_2,  

      output [15:0] reg3,
      output [15:0] reg4
 );  
      reg     [15:0]     reg_array [7:0];  //8 registers that can hold 16bits of information
      // write port  
      //reg [2:0] i;  
      always @ (posedge clk or posedge rst) begin  
           if(rst) begin  
                reg_array[0] <= 16'b0;  
                reg_array[1] <= 16'b0100;  
                reg_array[2] <= 16'b1;  
                reg_array[3] <= 16'b0;  
                reg_array[4] <= 16'b0;  
                reg_array[5] <= 16'b0;  
                reg_array[6] <= 16'b0;  
                reg_array[7] <= 16'b0;       
           end  
           else begin  
                if(reg_write_en) begin  
                     reg_array[reg_write_dest] <= reg_write_data;  
                end  
           end  
      end  
      assign reg_read_data_1 = ( reg_read_addr_1 == 0)? 16'b0 : reg_array[reg_read_addr_1];  //when read address is 0, we return nothing as read data...
      assign reg_read_data_2 = ( reg_read_addr_2 == 0)? 16'b0 : reg_array[reg_read_addr_2];  
      assign reg3 = reg_array[2];
      assign reg4 = reg_array[3];
 endmodule




// tells processor if we are jumping or not jumping based on the current instruction
module JR_Control( input[1:0] alu_op, 
       input [3:0] funct,
       output JRControl
    );
assign JRControl = ({alu_op,funct}==6'b001000) ? 1'b1 : 1'b0;
endmodule



 //Control unit, sends out control lines to processor based on opcode input 
 module control( input[2:0] opcode,  
                           input reset,  

                           //following are list of control lines
                            //(some control lines are 2 bits instead of just 1)
                           output reg[1:0] reg_dst,mem_to_reg,alu_op,  
                           output reg jump,branch,mem_read,mem_write,alu_src,reg_write,sign_or_zero      
                                           
   );  
 always @(*)  
 begin  
      if(reset == 1'b1) begin  
                reg_dst = 2'b00;  
                mem_to_reg = 2'b00;  
                alu_op = 2'b00;  
                jump = 1'b0;  
                branch = 1'b0;  
                mem_read = 1'b0;  
                mem_write = 1'b0;  
                alu_src = 1'b0;  
                reg_write = 1'b0;  
                sign_or_zero = 1'b1;  
      end  
      else begin  
      case(opcode)   
      3'b000: begin // add  
                reg_dst = 2'b01;  
                mem_to_reg = 2'b00;  
                alu_op = 2'b00;  
                jump = 1'b0;  
                branch = 1'b0;  
                mem_read = 1'b0;  
                mem_write = 1'b0;  
                alu_src = 1'b0;  
                reg_write = 1'b1;  
                sign_or_zero = 1'b1;  
                end  
      3'b001: begin // sli  
                reg_dst = 2'b00;  
                mem_to_reg = 2'b00;  
                alu_op = 2'b10;  
                jump = 1'b0;  
                branch = 1'b0;  
                mem_read = 1'b0;  
                mem_write = 1'b0;  
                alu_src = 1'b1;  
                reg_write = 1'b1;  
                sign_or_zero = 1'b0;  
                end  
      3'b010: begin // j  
                reg_dst = 2'b00;  
                mem_to_reg = 2'b00;  
                alu_op = 2'b00;  
                jump = 1'b1;  
                branch = 1'b0;  
                mem_read = 1'b0;  
                mem_write = 1'b0;  
                alu_src = 1'b0;  
                reg_write = 1'b0;  
                sign_or_zero = 1'b1;  
                end  
      3'b011: begin // jal  
                reg_dst = 2'b10;  
                mem_to_reg = 2'b10;  
                alu_op = 2'b00;  
                jump = 1'b1;  
                branch = 1'b0;  
                mem_read = 1'b0;  
                mem_write = 1'b0;  
                alu_src = 1'b0;  
                reg_write = 1'b1;  
                sign_or_zero = 1'b1;  
                end  
      3'b100: begin // lw  
                reg_dst = 2'b00;  
                mem_to_reg = 2'b01;  
                alu_op = 2'b11;  
                jump = 1'b0;  
                branch = 1'b0;  
                mem_read = 1'b1;  
                mem_write = 1'b0;  
                alu_src = 1'b1;  
                reg_write = 1'b1;  
                sign_or_zero = 1'b1;  
                end  
      3'b101: begin // sw  
                reg_dst = 2'b00;  
                mem_to_reg = 2'b00;  
                alu_op = 2'b11;  
                jump = 1'b0;  
                branch = 1'b0;  
                mem_read = 1'b0;  
                mem_write = 1'b1;  
                alu_src = 1'b1;  
                reg_write = 1'b0;  
                sign_or_zero = 1'b1;  
                end  
      3'b110: begin // beq  
                reg_dst = 2'b00;  
                mem_to_reg = 2'b00;  
                alu_op = 2'b01;  
                jump = 1'b0;  
                branch = 1'b1;  
                mem_read = 1'b0;  
                mem_write = 1'b0;  
                alu_src = 1'b0;  
                reg_write = 1'b0;  
                sign_or_zero = 1'b1;  
                end  
      3'b111: begin // addi  
                reg_dst = 2'b00;  
                mem_to_reg = 2'b00;  
                alu_op = 2'b11;  
                jump = 1'b0;  
                branch = 1'b0;  
                mem_read = 1'b0;  
                mem_write = 1'b0;  
                alu_src = 1'b1;  
                reg_write = 1'b1;  
                sign_or_zero = 1'b1;  
                end  
      default: begin  
                reg_dst = 2'b01;  
                mem_to_reg = 2'b00;  
                alu_op = 2'b00;  
                jump = 1'b0;  
                branch = 1'b0;  
                mem_read = 1'b0;  
                mem_write = 1'b0;  
                alu_src = 1'b0;  
                reg_write = 1'b1;  
                sign_or_zero = 1'b1;  
                end  
      endcase  
      end  
 end  
 endmodule  




//interface control unit, alu_control unit, and Data memory unit 
//implements the processing of the result within a single clock cycle 
module mips_16( input clk,reset,  
                           output[15:0] pc_out, alu_result
                            ,reg3,reg4  
   );  
 reg[15:0] pc_current;  
 wire signed[15:0] pc_next,pc2;  
 wire [15:0] instr;  
 wire[1:0] reg_dst,mem_to_reg,alu_op;  
 wire jump,branch,mem_read,mem_write,alu_src,reg_write     ;  
 wire     [2:0]     reg_write_dest;  
 wire     [15:0] reg_write_data;  
 wire     [2:0]     reg_read_addr_1;  
 wire     [15:0] reg_read_data_1;  
 wire     [2:0]     reg_read_addr_2;  
 wire     [15:0] reg_read_data_2;  
 wire [15:0] sign_ext_im,read_data2,zero_ext_im,imm_ext;  
 wire JRControl;  
 wire [2:0] ALU_Control;  
 wire [15:0] ALU_out;  
 wire zero_flag;  
 wire signed[15:0] im_shift_1, PC_j, PC_beq, PC_4beq,PC_4beqj,PC_jr;  
 wire beq_control;  
 wire [14:0] jump_shift_1;  
 wire [15:0]mem_read_data;  
 wire [15:0] no_sign_ext;  
 wire sign_or_zero;  
 // PC   
 always @(posedge clk or posedge reset)  
 begin   
      if(reset)   
           pc_current <= 16'd0;  
      else  
           pc_current <= pc_next;  
 end  
 // PC + 2   
 assign pc2 = pc_current + 16'd2;  
 // instruction memory  
 instr_mem instrucion_memory(.pc(pc_current),.instruction(instr));  
 // jump shift left 1  
 assign jump_shift_1 = {instr[13:0],1'b0};  
 // control unit  
 control control_unit(.reset(reset),.opcode(instr[15:13]),.reg_dst(reg_dst)  
                ,.mem_to_reg(mem_to_reg),.alu_op(alu_op),.jump(jump),.branch(branch),.mem_read(mem_read),  
                .mem_write(mem_write),.alu_src(alu_src),.reg_write(reg_write),.sign_or_zero(sign_or_zero));  
 // multiplexer regdest  
 assign reg_write_dest = (reg_dst==2'b10) ? 3'b111: ((reg_dst==2'b01) ? instr[6:4] :instr[9:7]);  
 // register file  
 assign reg_read_addr_1 = instr[12:10];  
 assign reg_read_addr_2 = instr[9:7];  
 register_file reg_file(.clk(clk),.rst(reset),.reg_write_en(reg_write),  
 .reg_write_dest(reg_write_dest),  
 .reg_write_data(reg_write_data),  
 .reg_read_addr_1(reg_read_addr_1),  
 .reg_read_data_1(reg_read_data_1),  
 .reg_read_addr_2(reg_read_addr_2),  
 .reg_read_data_2(reg_read_data_2),
 .reg3(reg3),  
 .reg4(reg4));  
 // sign extend  
 assign sign_ext_im = {{9{instr[6]}},instr[6:0]};  
 assign zero_ext_im = {{9{1'b0}},instr[6:0]};  
 assign imm_ext = (sign_or_zero==1'b1) ? sign_ext_im : zero_ext_im;  
 // JR control  
 JR_Control JRControl_unit(.alu_op(alu_op),.funct(instr[3:0]),.JRControl(JRControl));       
 // ALU control unit  
 ALUControl ALU_Control_unit(.ALUOp(alu_op),.Function(instr[3:0]),.ALU_Control(ALU_Control));  
 // multiplexer alu_src  
 assign read_data2 = (alu_src==1'b1) ? imm_ext : reg_read_data_2;  
 // ALU   
 alu alu_unit(.a(reg_read_data_1),.b(read_data2),.alu_control(ALU_Control),.result(ALU_out),.zero(zero_flag));  
 // immediate shift 1  
 assign im_shift_1 = {imm_ext[14:0],1'b0};  
 //  
 assign no_sign_ext = ~(im_shift_1) + 1'b1;  
 // PC beq add  
 assign PC_beq = (im_shift_1[15] == 1'b1) ? (pc2 - no_sign_ext): (pc2 +im_shift_1); 
 // beq control  
 assign beq_control = branch & zero_flag;  
 // PC_beq  
 assign PC_4beq = (beq_control==1'b1) ? PC_beq : pc2;  
 // PC_j  
 assign PC_j = {pc2[15],jump_shift_1};  
 // PC_4beqj  
 assign PC_4beqj = (jump == 1'b1) ? PC_j : PC_4beq;  
 // PC_jr  
 assign PC_jr = reg_read_data_1;  
 // PC_next  
 assign pc_next = (JRControl==1'b1) ? PC_jr : PC_4beqj;  
 // data memory  
 data_memory datamem(.clk(clk),.mem_access_addr(ALU_out),  
 .mem_write_data(reg_read_data_2),.mem_write_en(mem_write),.mem_read(mem_read),  
 .mem_read_data(mem_read_data));  
 // write back  
 assign reg_write_data = (mem_to_reg == 2'b10) ? pc2:((mem_to_reg == 2'b01)? mem_read_data: ALU_out);  
 // output  
 assign pc_out = pc_current;  
 assign alu_result = ALU_out;  

 endmodule

CS3650_P1_SingleCycle/instruction_memory_mod.v

//holds the instruction list of our program i guess
module instr_mem          // a synthesisable rom implementation  
 (  
      input     [15:0]     pc,  
      output wire     [15:0]          instruction  
 );  
      wire [3 : 0] rom_addr = pc[4 : 1];  
      /* lw     $3, 0($0) --   
           Loop:     slti $1, $3, 50  
           beq $1, $0, Skip  
           add $4, $4, $3   
           addi $3, $3, 1   
           beq $0, $0, Loop--  
           Skip  
 */  
      reg [15:0] rom[15:0];  
      initial  
      begin  
                rom[0] = 16'b1000000110000000; //8180 
               //  rom[1] = 16'b0010110010110010; //2CB2
                rom[1] = 16'b0000010100110000; //add together reg 1 to register 2 into register 3 (expected result: 4+1 = 5 based on reg initial vals)
                rom[2] = 16'b1101110001100111; //DC67 11001110 + 0000110 = 11010100 (212)= PCbranch target address -> way out of scope from here, so "skip"
                rom[3] = 16'b1101110111011001; //DDD9
                rom[4] = 16'b1111110110110001;  
                rom[5] = 16'b1100000001111011; 
                rom[6] = 16'b0000000000000000;  
                rom[7] = 16'b0000000000000000;  
                rom[8] = 16'b0000000000000000;  
                rom[9] = 16'b0000000000000000;  
                rom[10] = 16'b0000000000000000;  
                rom[11] = 16'b0000000000000000;  
                rom[12] = 16'b0000000000000000;  
                rom[13] = 16'b0000000000000000;  
                rom[14] = 16'b0000000000000000;  
                rom[15] = 16'b0000000000000000;  
      end  
      assign instruction = (pc[15:0] < 32 )? rom[rom_addr[3:0]]: 16'd0;  
 endmodule

CS3650_P1_SingleCycle/proccessor_tb.v
 `timescale 1ns / 1ps
//~~Compile
// iverilog -o testbench.vvp testbench.v
// vvp testbench.vvp

//fpga4student.com: FPGA projects, Verilog projects, VHDL projects
// Verilog project: Verilog code for 16-bit MIPS Processor
// Testbench Verilog code for 16 bit single cycle MIPS CPU  

`include "processor_module.v"

 module tb_mips16;  
      // Inputs  
      reg clk;  
      reg reset;  
      // Outputs  
      wire [15:0] pc_out;  
      wire [15:0] alu_result;//,reg3,reg4;  
      // Instantiate the Unit Under Test (UUT)  

      wire [15:0] reg3;
      wire [15:0] reg4;
      mips_16 uut (  
           .clk(clk),   
           .reset(reset),   
           .pc_out(pc_out),   
           .alu_result(alu_result),  
           .reg3(reg3),  
           .reg4(reg4)  
      );  
      initial begin  

           clk = 0;  
           forever #10 clk = ~clk;  
      end  
      initial begin  
          $dumpfile("dump.vcd");
          $dumpvars(0, tb_mips16);
        // Initialize Inputs  
        $monitor ("register 3=%d, register 4=%d", reg3,reg4);  
        reset = 1;  
        // Wait 100 ns for global reset to finish  
        #100;  
        reset = 0;  
        // Add stimulus here  
      end  
 endmodule

CS3650_P1_SingleCycle/dump.vcd
$date
	Sun Nov 27 00:13:18 2022
$end
$version
	Icarus Verilog
$end
$timescale
	1ps
$end
$scope module tb_mips16 $end
$var wire 16 ! reg4 [15:0] $end
$var wire 16 " reg3 [15:0] $end
$var wire 16 # pc_out [15:0] $end
$var wire 16 $ alu_result [15:0] $end
$var reg 1 % clk $end
$var reg 1 & reset $end
$scope module uut $end
$var wire 16 ' PC_jr [15:0] $end
$var wire 16 ( alu_result [15:0] $end
$var wire 1 ) beq_control $end
$var wire 1 % clk $end
$var wire 16 * pc_out [15:0] $end
$var wire 1 & reset $end
$var wire 1 + zero_flag $end
$var wire 16 , zero_ext_im [15:0] $end
$var wire 1 - sign_or_zero $end
$var wire 16 . sign_ext_im [15:0] $end
$var wire 3 / reg_write_dest [2:0] $end
$var wire 16 0 reg_write_data [15:0] $end
$var wire 1 1 reg_write $end
$var wire 16 2 reg_read_data_2 [15:0] $end
$var wire 16 3 reg_read_data_1 [15:0] $end
$var wire 3 4 reg_read_addr_2 [2:0] $end
$var wire 3 5 reg_read_addr_1 [2:0] $end
$var wire 2 6 reg_dst [1:0] $end
$var wire 16 7 reg4 [15:0] $end
$var wire 16 8 reg3 [15:0] $end
$var wire 16 9 read_data2 [15:0] $end
$var wire 16 : pc_next [15:0] $end
$var wire 16 ; pc2 [15:0] $end
$var wire 16 < no_sign_ext [15:0] $end
$var wire 1 = mem_write $end
$var wire 2 > mem_to_reg [1:0] $end
$var wire 16 ? mem_read_data [15:0] $end
$var wire 1 @ mem_read $end
$var wire 15 A jump_shift_1 [14:0] $end
$var wire 1 B jump $end
$var wire 16 C instr [15:0] $end
$var wire 16 D imm_ext [15:0] $end
$var wire 16 E im_shift_1 [15:0] $end
$var wire 1 F branch $end
$var wire 1 G alu_src $end
$var wire 2 H alu_op [1:0] $end
$var wire 16 I PC_j [15:0] $end
$var wire 16 J PC_beq [15:0] $end
$var wire 16 K PC_4beqj [15:0] $end
$var wire 16 L PC_4beq [15:0] $end
$var wire 1 M JRControl $end
$var wire 16 N ALU_out [15:0] $end
$var wire 3 O ALU_Control [2:0] $end
$var reg 16 P pc_current [15:0] $end
$scope module ALU_Control_unit $end
$var wire 4 Q Function [3:0] $end
$var wire 2 R ALUOp [1:0] $end
$var wire 6 S ALUControlIn [5:0] $end
$var reg 3 T ALU_Control [2:0] $end
$upscope $end
$scope module JRControl_unit $end
$var wire 4 U funct [3:0] $end
$var wire 2 V alu_op [1:0] $end
$var wire 1 M JRControl $end
$upscope $end
$scope module alu_unit $end
$var wire 3 W alu_control [2:0] $end
$var wire 16 X b [15:0] $end
$var wire 1 + zero $end
$var wire 16 Y a [15:0] $end
$var reg 16 Z result [15:0] $end
$upscope $end
$scope module control_unit $end
$var wire 3 [ opcode [2:0] $end
$var wire 1 & reset $end
$var reg 2 \ alu_op [1:0] $end
$var reg 1 G alu_src $end
$var reg 1 F branch $end
$var reg 1 B jump $end
$var reg 1 @ mem_read $end
$var reg 2 ] mem_to_reg [1:0] $end
$var reg 1 = mem_write $end
$var reg 2 ^ reg_dst [1:0] $end
$var reg 1 1 reg_write $end
$var reg 1 - sign_or_zero $end
$upscope $end
$scope module datamem $end
$var wire 1 % clk $end
$var wire 16 _ mem_access_addr [15:0] $end
$var wire 1 @ mem_read $end
$var wire 1 = mem_write_en $end
$var wire 8 ` ram_addr [7:0] $end
$var wire 16 a mem_write_data [15:0] $end
$var wire 16 b mem_read_data [15:0] $end
$var integer 32 c i [31:0] $end
$upscope $end
$scope module instrucion_memory $end
$var wire 16 d pc [15:0] $end
$var wire 4 e rom_addr [3:0] $end
$var wire 16 f instruction [15:0] $end
$upscope $end
$scope module reg_file $end
$var wire 1 % clk $end
$var wire 16 g reg3 [15:0] $end
$var wire 16 h reg4 [15:0] $end
$var wire 3 i reg_read_addr_1 [2:0] $end
$var wire 3 j reg_read_addr_2 [2:0] $end
$var wire 16 k reg_write_data [15:0] $end
$var wire 3 l reg_write_dest [2:0] $end
$var wire 1 1 reg_write_en $end
$var wire 1 & rst $end
$var wire 16 m reg_read_data_2 [15:0] $end
$var wire 16 n reg_read_data_1 [15:0] $end
$upscope $end
$upscope $end
$upscope $end
$enddefinitions $end
$comment Show the parameter values. $end
$dumpall
$end
#0
$dumpvars
b0 n
b0 m
b11 l
b0 k
b11 j
b0 i
b0 h
b1 g
b1000000110000000 f
b0 e
b0 d
b100000000 c
b0 b
b0 a
b0 `
b0 _
b0 ^
b0 ]
b0 \
b100 [
b0 Z
b0 Y
b0 X
b0 W
b0 V
b0 U
b0 T
b0 S
b0 R
b0 Q
b0 P
b0 O
b0 N
0M
b10 L
b10 K
b10 J
b1100000000 I
b0 H
0G
0F
b0 E
b0 D
b1000000110000000 C
0B
b1100000000 A
0@
b0 ?
b0 >
0=
b0 <
b10 ;
b10 :
b0 9
b1 8
b0 7
b0 6
b0 5
b11 4
b0 3
b0 2
01
b0 0
b11 /
b0 .
1-
b0 ,
1+
b0 *
0)
b0 (
b0 '
1&
0%
b0 $
b0 #
b1 "
b0 !
$end
#10000
1%
#20000
0%
#30000
1%
#40000
0%
#50000
1%
#60000
0%
#70000
1%
#80000
0%
#90000
1%
#100000
11
1G
1@
b110000 S
b11 H
b11 R
b11 V
b11 \
b1 >
b1 ]
0%
0&
#110000
b101 0
b101 k
b1111111110100000 <
0+
b10 `
b1 9
b1 X
b1100000 E
b101 $
b101 (
b101 N
b101 Z
b101 _
b110000 D
b1 2
b1 a
b1 m
b100 '
b100 3
b100 Y
b100 n
0G
0@
b0 S
b0 H
b0 R
b0 V
b0 \
b0 >
b0 ]
b1 6
b1 ^
b100 :
b110000 ,
b110000 .
b10 4
b10 j
b1 5
b1 i
b0 [
b101001100000 I
b101001100000 A
b100 K
b10100110000 C
b10100110000 f
b1100100 J
b100 L
b1 e
b100 ;
b10 #
b10 *
b10 P
b10 d
1%
#120000
0%
#130000
1)
1+
b0 0
b0 k
b110010 <
b0 `
b1111111111001110 E
b0 9
b0 X
b0 $
b0 (
b0 N
b0 Z
b0 _
b0 /
b0 l
b1 O
b1 T
b1 W
b1111111111100111 D
b0 2
b0 a
b0 m
b0 '
b0 3
b0 Y
b0 n
01
1F
b1 H
b1 R
b1 V
b1 \
b0 6
b0 ^
b1111111111010100 :
b10111 S
b111 Q
b111 U
b1100111 ,
b1111111111100111 .
b0 4
b0 j
b111 5
b111 i
b110 [
b11100011001110 I
b11100011001110 A
b1111111111010100 K
b1101110001100111 C
b1101110001100111 f
b1111111111010100 J
b1111111111010100 L
b10 e
b110 ;
b100 #
b100 *
b100 P
b100 d
b101 !
b101 7
b101 h
1%
#140000
0%
#150000
b0 <
b1111111111010110 :
b0 E
0)
b1111111111010110 K
b0 O
b0 T
b0 W
b0 D
11
0F
b0 H
b0 R
b0 V
b0 \
b1 6
b1 ^
b1111111111010110 L
b0 S
b0 Q
b0 U
b0 ,
b0 .
b0 5
b0 i
b0 [
b0 A
b1111111111010110 J
b1000000000000000 I
b1010 e
b0 C
b0 f
b1111111111010110 ;
b1111111111010100 #
b1111111111010100 *
b1111111111010100 P
b1111111111010100 d
1%
#160000
0%
#170000
b1111111111011000 :
b1111111111011000 K
b1111111111011000 J
b1111111111011000 L
b1011 e
b1111111111011000 ;
b1111111111010110 #
b1111111111010110 *
b1111111111010110 P
b1111111111010110 d
1%
#180000
0%
#190000
b1111111111011010 :
b1111111111011010 K
b1111111111011010 J
b1111111111011010 L
b1100 e
b1111111111011010 ;
b1111111111011000 #
b1111111111011000 *
b1111111111011000 P
b1111111111011000 d
1%
#200000
0%
#210000
b1111111111011100 :
b1111111111011100 K
b1111111111011100 J
b1111111111011100 L
b1101 e
b1111111111011100 ;
b1111111111011010 #
b1111111111011010 *
b1111111111011010 P
b1111111111011010 d
1%
#220000
0%
#230000
b1111111111011110 :
b1111111111011110 K
b1111111111011110 J
b1111111111011110 L
b1110 e
b1111111111011110 ;
b1111111111011100 #
b1111111111011100 *
b1111111111011100 P
b1111111111011100 d
1%
#240000
0%
#250000
b1111111111100000 :
b1111111111100000 K
b1111111111100000 J
b1111111111100000 L
b1111 e
b1111111111100000 ;
b1111111111011110 #
b1111111111011110 *
b1111111111011110 P
b1111111111011110 d
1%
#260000
0%
#270000
b1111111111100010 :
b1111111111100010 K
b1111111111100010 J
b1111111111100010 L
b0 e
b1111111111100010 ;
b1111111111100000 #
b1111111111100000 *
b1111111111100000 P
b1111111111100000 d
1%
#280000
0%
#290000
b1111111111100100 :
b1111111111100100 K
b1111111111100100 J
b1111111111100100 L
b1 e
b1111111111100100 ;
b1111111111100010 #
b1111111111100010 *
b1111111111100010 P
b1111111111100010 d
1%
#300000
0%
#310000
b1111111111100110 :
b1111111111100110 K
b1111111111100110 J
b1111111111100110 L
b10 e
b1111111111100110 ;
b1111111111100100 #
b1111111111100100 *
b1111111111100100 P
b1111111111100100 d
1%
#320000
0%
#330000
b1111111111101000 :
b1111111111101000 K
b1111111111101000 J
b1111111111101000 L
b11 e
b1111111111101000 ;
b1111111111100110 #
b1111111111100110 *
b1111111111100110 P
b1111111111100110 d
1%
#340000
0%
#350000
b1111111111101010 :
b1111111111101010 K
b1111111111101010 J
b1111111111101010 L
b100 e
b1111111111101010 ;
b1111111111101000 #
b1111111111101000 *
b1111111111101000 P
b1111111111101000 d
1%
#360000
0%
#370000
b1111111111101100 :
b1111111111101100 K
b1111111111101100 J
b1111111111101100 L
b101 e
b1111111111101100 ;
b1111111111101010 #
b1111111111101010 *
b1111111111101010 P
b1111111111101010 d
1%
#380000
0%
#390000
b1111111111101110 :
b1111111111101110 K
b1111111111101110 J
b1111111111101110 L
b110 e
b1111111111101110 ;
b1111111111101100 #
b1111111111101100 *
b1111111111101100 P
b1111111111101100 d
1%
#400000
0%
#410000
b1111111111110000 :
b1111111111110000 K
b1111111111110000 J
b1111111111110000 L
b111 e
b1111111111110000 ;
b1111111111101110 #
b1111111111101110 *
b1111111111101110 P
b1111111111101110 d
1%
#420000
0%
#430000
b1111111111110010 :
b1111111111110010 K
b1111111111110010 J
b1111111111110010 L
b1000 e
b1111111111110010 ;
b1111111111110000 #
b1111111111110000 *
b1111111111110000 P
b1111111111110000 d
1%
#440000
0%
#450000
b1111111111110100 :
b1111111111110100 K
b1111111111110100 J
b1111111111110100 L
b1001 e
b1111111111110100 ;
b1111111111110010 #
b1111111111110010 *
b1111111111110010 P
b1111111111110010 d
1%
#460000
0%
#470000
b1111111111110110 :
b1111111111110110 K
b1111111111110110 J
b1111111111110110 L
b1010 e
b1111111111110110 ;
b1111111111110100 #
b1111111111110100 *
b1111111111110100 P
b1111111111110100 d
1%
#480000
0%
#490000
b1111111111111000 :
b1111111111111000 K
b1111111111111000 J
b1111111111111000 L
b1011 e
b1111111111111000 ;
b1111111111110110 #
b1111111111110110 *
b1111111111110110 P
b1111111111110110 d
1%
#500000
0%
#510000
b1111111111111010 :
b1111111111111010 K
b1111111111111010 J
b1111111111111010 L
b1100 e
b1111111111111010 ;
b1111111111111000 #
b1111111111111000 *
b1111111111111000 P
b1111111111111000 d
1%
#520000
0%
#530000
b1111111111111100 :
b1111111111111100 K
b1111111111111100 J
b1111111111111100 L
b1101 e
b1111111111111100 ;
b1111111111111010 #
b1111111111111010 *
b1111111111111010 P
b1111111111111010 d
1%
#540000
0%
#550000
b1111111111111110 :
b1111111111111110 K
b1111111111111110 J
b1111111111111110 L
b1110 e
b1111111111111110 ;
b1111111111111100 #
b1111111111111100 *
b1111111111111100 P
b1111111111111100 d
1%
#560000
0%
#570000
b0 :
b0 K
b0 J
b0 L
b0 I
b1111 e
b0 ;
b1111111111111110 #
b1111111111111110 *
b1111111111111110 P
b1111111111111110 d
1%
#580000
0%
#590000
b11 /
b11 l
b101 2
b101 a
b101 m
1G
1@
b110000 S
b11 H
b11 R
b11 V
b11 \
b1 >
b1 ]
b0 6
b0 ^
b10 :
b11 4
b11 j
b100 [
b1100000000 I
b1100000000 A
b10 K
b1000000110000000 C
b1000000110000000 f
b10 J
b10 L
b0 e
b10 ;
b0 #
b0 *
b0 P
b0 d
1%
#600000
0%
#610000
b101 0
b101 k
b1111111110100000 <
0+
b10 `
b1 9
b1 X
b1100000 E
b101 $
b101 (
b101 N
b101 Z
b101 _
b110000 D
b100 '
b100 3
b100 Y
b100 n
0G
0@
b0 S
b0 H
b0 R
b0 V
b0 \
b0 >
b0 ]
b1 6
b1 ^
b100 :
b110000 ,
b110000 .
b10 4
b10 j
b1 5
b1 i
b0 [
b101001100000 I
b101001100000 A
b100 K
b10100110000 C
b10100110000 f
b1100100 J
b100 L
b1 e
b1 2
b1 a
b1 m
b100 ;
b10 #
b10 *
b10 P
b10 d
b0 !
b0 7
b0 h
1%
#620000
0%
#630000
1)
1+
b0 0
b0 k
b110010 <
b0 `
b1111111111001110 E
b0 9
b0 X
b0 $
b0 (
b0 N
b0 Z
b0 _
b0 /
b0 l
b1 O
b1 T
b1 W
b1111111111100111 D
b0 2
b0 a
b0 m
b0 '
b0 3
b0 Y
b0 n
01
1F
b1 H
b1 R
b1 V
b1 \
b0 6
b0 ^
b1111111111010100 :
b10111 S
b111 Q
b111 U
b1100111 ,
b1111111111100111 .
b0 4
b0 j
b111 5
b111 i
b110 [
b11100011001110 I
b11100011001110 A
b1111111111010100 K
b1101110001100111 C
b1101110001100111 f
b1111111111010100 J
b1111111111010100 L
b10 e
b101 !
b101 7
b101 h
b110 ;
b100 #
b100 *
b100 P
b100 d
1%
#640000
0%
#650000
b0 <
b1111111111010110 :
b0 E
0)
b1111111111010110 K
b0 O
b0 T
b0 W
b0 D
11
0F
b0 H
b0 R
b0 V
b0 \
b1 6
b1 ^
b1111111111010110 L
b0 S
b0 Q
b0 U
b0 ,
b0 .
b0 5
b0 i
b0 [
b0 A
b1111111111010110 J
b1000000000000000 I
b1010 e
b0 C
b0 f
b1111111111010110 ;
b1111111111010100 #
b1111111111010100 *
b1111111111010100 P
b1111111111010100 d
1%
#660000
0%
#670000
b1111111111011000 :
b1111111111011000 K
b1111111111011000 J
b1111111111011000 L
b1011 e
b1111111111011000 ;
b1111111111010110 #
b1111111111010110 *
b1111111111010110 P
b1111111111010110 d
1%
#680000
0%
#690000
b1111111111011010 :
b1111111111011010 K
b1111111111011010 J
b1111111111011010 L
b1100 e
b1111111111011010 ;
b1111111111011000 #
b1111111111011000 *
b1111111111011000 P
b1111111111011000 d
1%
#700000
0%
#710000
b1111111111011100 :
b1111111111011100 K
b1111111111011100 J
b1111111111011100 L
b1101 e
b1111111111011100 ;
b1111111111011010 #
b1111111111011010 *
b1111111111011010 P
b1111111111011010 d
1%
#720000
0%
#730000
b1111111111011110 :
b1111111111011110 K
b1111111111011110 J
b1111111111011110 L
b1110 e
b1111111111011110 ;
b1111111111011100 #
b1111111111011100 *
b1111111111011100 P
b1111111111011100 d
1%
#740000
0%
#750000
b1111111111100000 :
b1111111111100000 K
b1111111111100000 J
b1111111111100000 L
b1111 e
b1111111111100000 ;
b1111111111011110 #
b1111111111011110 *
b1111111111011110 P
b1111111111011110 d
1%
#760000
0%
#770000
b1111111111100010 :
b1111111111100010 K
b1111111111100010 J
b1111111111100010 L
b0 e
b1111111111100010 ;
b1111111111100000 #
b1111111111100000 *
b1111111111100000 P
b1111111111100000 d
1%
#780000
0%
